pdbbasic/__init__.py
pdbbasic/frame.py
pdbbasic/geometric.py
pdbbasic/mmcif_utils.py
pdbbasic/pdbio.py
pdbbasic/quaternion.py
pdbbasic/rmsd.py
pdbbasic/utils.py
pdbbasic-0.8.0.dist-info/LICENSE
pdbbasic-0.8.0.dist-info/METADATA
pdbbasic-0.8.0.dist-info/WHEEL
pdbbasic-0.8.0.dist-info/top_level.txt
pdbbasic-0.8.0.dist-info/RECORD
