Metadata-Version: 2.1
Name: pdbbasic
Version: 0.8.0
Summary: Basic Utilities for Protein Structure Data
Home-page: https://github.com/ShintaroMinami/PDBBasic
Author: Shintaro Minami
Author-email: shintaro.minami@gmail.com
License: MIT
Classifier: License :: OSI Approved :: MIT License
Classifier: Programming Language :: Python :: 3.8
License-File: LICENSE
Requires-Dist: numpy
Requires-Dist: pandas
Requires-Dist: torch
Requires-Dist: einops
Requires-Dist: pdbecif
